[
    {
        "index": 0,
        "previous hash": null,
        "dificulty": 0,
        "work level": 0,
        "data": {
            "blockType": "Genesis Block"
        },
        "hash": "0dff3409342d0d8b219a234d6fd45a05d4c777b1180055fe56e32af8ca3a95df"
    },
    {
        "index": 1,
        "previous hash": "0dff3409342d0d8b219a234d6fd45a05d4c777b1180055fe56e32af8ca3a95df",
        "dificulty": 2,
        "work level": 192,
        "data": {
            "id": 9,
            "auction_id": 21,
            "amount": "1",
            "status": 0,
            "date_placed": "2020/2/19",
            "expected_date": "2020-02-25",
            "buyer": 4,
            "employee": 8,
            "shipping_address": null,
            "shipping_id": null
        },
        "hash": "00a3f975ad2d9b5cb134419e9fb796903764ab5b593ad4cd630853e54ec94059"
    }
]